odoo/addons/sale_product_pack/README.rst
odoo/addons/sale_product_pack/__init__.py
odoo/addons/sale_product_pack/__manifest__.py
odoo/addons/sale_product_pack/demo/product_pack_line_demo.xml
odoo/addons/sale_product_pack/i18n/ca.po
odoo/addons/sale_product_pack/i18n/ca_ES.po
odoo/addons/sale_product_pack/i18n/es.po
odoo/addons/sale_product_pack/i18n/fr.po
odoo/addons/sale_product_pack/i18n/pt.po
odoo/addons/sale_product_pack/i18n/sale_product_pack.pot
odoo/addons/sale_product_pack/models/__init__.py
odoo/addons/sale_product_pack/models/product_pack_line.py
odoo/addons/sale_product_pack/models/sale_order.py
odoo/addons/sale_product_pack/models/sale_order_line.py
odoo/addons/sale_product_pack/readme/CONTRIBUTORS.rst
odoo/addons/sale_product_pack/readme/DESCRIPTION.rst
odoo/addons/sale_product_pack/readme/ROADMAP.rst
odoo/addons/sale_product_pack/readme/USAGE.rst
odoo/addons/sale_product_pack/security/ir.model.access.csv
odoo/addons/sale_product_pack/static/description/icon.png
odoo/addons/sale_product_pack/static/description/index.html
odoo/addons/sale_product_pack/tests/__init__.py
odoo/addons/sale_product_pack/tests/test_sale_product_pack.py
odoo/addons/sale_product_pack/views/product_pack_line_views.xml
odoo12_addon_sale_product_pack-12.0.1.1.2.dist-info/METADATA
odoo12_addon_sale_product_pack-12.0.1.1.2.dist-info/WHEEL
odoo12_addon_sale_product_pack-12.0.1.1.2.dist-info/top_level.txt
odoo12_addon_sale_product_pack-12.0.1.1.2.dist-info/RECORD
